rolypoly/__init__.py
rolypoly/rolypoly.py
rolypoly/rpconfig.json
rolypoly/commands/__init__
rolypoly/commands/annotation/annotate.py
rolypoly/commands/annotation/annotate_RNA.py
rolypoly/commands/annotation/annotate_prot.py
rolypoly/commands/assembly/assemble.py
rolypoly/commands/assembly/co_assembly.py
rolypoly/commands/assembly/filter_contigs.py
rolypoly/commands/assembly/refinement.py
rolypoly/commands/bining/corrolate.py
rolypoly/commands/bining/termini.py
rolypoly/commands/host/classify.py
rolypoly/commands/identify_virus/marker_search.py
rolypoly/commands/identify_virus/search_viruses.py
rolypoly/commands/misc/add_command.py
rolypoly/commands/misc/build_data.py
rolypoly/commands/misc/end_2_end.py
rolypoly/commands/misc/fetch_sra_fastq.py
rolypoly/commands/misc/get_external_data.py
rolypoly/commands/misc/quick_taxonomy.py
rolypoly/commands/misc/rename_seqs.py
rolypoly/commands/misc/sequence_stats.py
rolypoly/commands/reads/__init__
rolypoly/commands/reads/filter_reads.py
rolypoly/commands/virotype/draw_rdrp_msa.py
rolypoly/commands/virotype/predict_characteristics.py
rolypoly/commands/virotype/summarize.py
rolypoly/commands/virotype/visualize.py
rolypoly/utils/__init__.py
rolypoly/utils/all_used_tools_dbs_citations.json
rolypoly/utils/citation_reminder.py
rolypoly/utils/config.py
rolypoly/utils/fax.py
rolypoly/utils/interval_ops.py
rolypoly/utils/lazy_group.py
rolypoly/utils/loggit.py
rolypoly/utils/output_tracker.py
rolypoly/utils/various.py
rolypoly/utils/benchmarking/get_data.py
rolypoly_bio-0.6.16.dist-info/METADATA
rolypoly_bio-0.6.16.dist-info/WHEEL
rolypoly_bio-0.6.16.dist-info/entry_points.txt
rolypoly_bio-0.6.16.dist-info/licenses/LICENSE
rolypoly_bio-0.6.16.dist-info/RECORD
