Metadata-Version: 2.4
Name: rolypoly_bio
Version: 0.6.16
Summary: RNA virus analysis toolkit
Project-URL: Source, https://code.jgi.doe.gov/rolypoly/rolypoly
Project-URL: Documentation, https://pages.jgi.doe.gov/rolypoly/docs/
Project-URL: pypi, https://pypi.org/project/rolypoly-bio/
Author-email: Uri Neri <uneri@lbl.gov>, Simon Roux <sroux@lbl.gov>, Brian Bushnell <bbushnell@lbl.gov>, Antonio Camargo <antoniop.camargo@lbl.gov>, Andrei Stecca Steindorff <andreiss@jgi.doe.gov>, Clement Coclet <cclement@jgi.doe.gov>, David Parker <dparker@carnegiescience.edu>, Dimitris Karapliafis <dimitris.karapliafis@atwur.nl>
License:                     GNU GENERAL PUBLIC LICENSE
License-File: LICENSE
Requires-Python: >=3.9
Requires-Dist: bbmapy<0.0.47,>=0.0.46
Requires-Dist: genomicranges<0.7,>=0.6.3
Requires-Dist: intervaltree<4,>=3.1.0
Requires-Dist: iranges<0.6,>=0.5.1
Requires-Dist: lightmotif<0.11,>=0.10.0
Requires-Dist: mappy<3,>=2.30
Requires-Dist: needletail<0.8,>=0.7.0
Requires-Dist: polars<2,>=1.31.0
Requires-Dist: psutil<8,>=7.0.0
Requires-Dist: pyfastx<3,>=2.2.0
Requires-Dist: pyhmmer<0.12,>=0.11.1
Requires-Dist: pyrodigal-gv<0.4,>=0.3.2
Requires-Dist: requests<3,>=2.32.4
Requires-Dist: rich-click<2,>=1.8.9
Requires-Dist: rich<15,>=14.0.0
Requires-Dist: viennarna<3,>=2.7.0
